Metadata-Version: 2.1
Name: crypto-connect
Version: 1.0.2
Summary: CLI tool to track cryptocurrencies
Home-page: https://iamkhattar.github.io/crypto-connect/#/
Author: Shivam Khattar <shivamkhattar1@gmail.com> , Khaled Alqallaf <kalqallaf1@outlook.com> , Saeed Khan <saeed786129@hotmail.com >
License: MIT
Download-URL: https://github.com/iamkhattar/crypto-connect/archive/1.0.2.tar.gz
Keywords: CLI,cryptocurrency,crypto currency,market trends
Platform: UNKNOWN
